faiss-1.5.3.data/purelib/faiss/__init__.py
faiss-1.5.3.data/purelib/faiss/__init__.pyc
faiss-1.5.3.data/purelib/faiss/_swigfaiss.so
faiss-1.5.3.data/purelib/faiss/swigfaiss.py
faiss-1.5.3.data/purelib/faiss/swigfaiss.pyc
faiss-1.5.3.dist-info/METADATA
faiss-1.5.3.dist-info/WHEEL
faiss-1.5.3.dist-info/top_level.txt
faiss-1.5.3.dist-info/RECORD
