Metadata-Version: 2.1
Name: faiss
Version: 1.5.3
Summary: A library for efficient similarity search and clustering of dense vectors
Home-page: https://github.com/facebookresearch/faiss
Author: Matthijs Douze, Jeff Johnson, Herve Jegou
Author-email: matthijs@fb.com
License: BSD
Keywords: search nearest neighbors
Platform: UNKNOWN
Classifier: Programming Language :: Python :: 2.7
Classifier: Programming Language :: Python :: 3.5
Classifier: Programming Language :: Python :: 3.6
Classifier: Programming Language :: Python :: 3.7
Requires-Dist: numpy
